nevada/__init__.py
nevada/API/Ad.py
nevada/API/AdExtension.py
nevada/API/AdKeyword.py
nevada/API/Adgroup.py
nevada/API/Bizmoney.py
nevada/API/BusinessChannel.py
nevada/API/Campaign.py
nevada/API/Estimate.py
nevada/API/IpExclusion.py
nevada/API/Label.py
nevada/API/LabelRef.py
nevada/API/ManagedCustomerLink.py
nevada/API/ManagedKeyword.py
nevada/API/MasterReport.py
nevada/API/RelKwdStat.py
nevada/API/Stat.py
nevada/API/StatReport.py
nevada/API/__init__.py
nevada/Common/Connector.py
nevada/Common/__init__.py
nevada-1.0.9.dist-info/LICENSE
nevada-1.0.9.dist-info/METADATA
nevada-1.0.9.dist-info/WHEEL
nevada-1.0.9.dist-info/top_level.txt
nevada-1.0.9.dist-info/RECORD
