Metadata-Version: 2.1
Name: nevada
Version: 1.0.9
Summary: For those who want to use Naver Search Ad easily.
Home-page: https://github.com/taegyumin/python_nevada
Author: Taegyu Min, Junho Song
Author-email: minimax@snu.ac.kr
License: MIT
Keywords: python_nevada,naver,search,ad
Platform: UNKNOWN
Classifier: License :: OSI Approved :: MIT License
Classifier: Topic :: Software Development :: Libraries
Classifier: Development Status :: 2 - Pre-Alpha
Classifier: Programming Language :: Python :: 3.4
Classifier: Programming Language :: Python :: 3.5
Classifier: Programming Language :: Python :: 3.6
Classifier: Programming Language :: Python :: 3.7
Classifier: Programming Language :: Python :: 3.8
Classifier: Programming Language :: Python :: 3 :: Only
Requires-Python: >=3.4
Requires-Dist: requests
Requires-Dist: jsonpickle
